cv_py/__init__.py
cv_py/resources/README.md
cv_py/resources/__init__.py
cv_py/resources/builtins.py
cv_py/resources/cord-tasks.yml
cv_py/resources/datapackage.py
cv_py/tools/__init__.py
cv_py/tools/process.py
cv_py/tools/remote.py
cv_py-0.2.1.dist-info/entry_points.txt
cv_py-0.2.1.dist-info/LICENSE.rst
cv_py-0.2.1.dist-info/WHEEL
cv_py-0.2.1.dist-info/METADATA
cv_py-0.2.1.dist-info/RECORD
